azure/__init__.py
azure/ai/__init__.py
azure/ai/mlmonitoring/__init__.py
azure/ai/mlmonitoring/collector.py
azure/ai/mlmonitoring/collector_base.py
azure/ai/mlmonitoring/collector_json.py
azure/ai/mlmonitoring/init.py
azure/ai/mlmonitoring/common/__init__.py
azure/ai/mlmonitoring/config/__init__.py
azure/ai/mlmonitoring/config/config.py
azure/ai/mlmonitoring/context/__init__.py
azure/ai/mlmonitoring/context/context.py
azure/ai/mlmonitoring/logger/__init__.py
azure/ai/mlmonitoring/logger/logger.py
azure/ai/mlmonitoring/payload/__init__.py
azure/ai/mlmonitoring/payload/factory.py
azure/ai/mlmonitoring/payload/logdata.py
azure/ai/mlmonitoring/payload/payload.py
azure/ai/mlmonitoring/queue/__init__.py
azure/ai/mlmonitoring/queue/queue.py
azure/ai/mlmonitoring/worker/__init__.py
azure/ai/mlmonitoring/worker/mdcsender.py
azure/ai/mlmonitoring/worker/printer.py
azure/ai/mlmonitoring/worker/sender.py
azure/ai/mlmonitoring/worker/worker.py
monitoring_sdk_helloworld-0.1.4.dist-info/METADATA
monitoring_sdk_helloworld-0.1.4.dist-info/WHEEL
monitoring_sdk_helloworld-0.1.4.dist-info/top_level.txt
monitoring_sdk_helloworld-0.1.4.dist-info/RECORD
